{"description":"O Geni torna a aprendizagem divertida para crianças dos 5 aos 10 anos. Com missões diárias que combinam exercícios de matemática e leitura guiada, as crianças desenvolvem competências essenciais enquanto se divertem.\n\nFUNCIONALIDADES:\n• Missões diárias de aprendizagem: conclua atividades de matemática e leitura todos os dias para ganhar recompensas\n• Exercícios de matemática: 20 exercícios por capítulo com adição, subtração, multiplicação e divisão\n• Leitura guiada: três modos, ler sozinho, ler para mim e ouvir-me ler com reconhecimento de voz\n• Dificuldade inteligente: as atividades adaptam-se automaticamente à idade e ao nível da criança\n• Recompensas divertidas: ganhe estrelas, moedas, XP e desbloqueie medalhas\n• Vários perfis: ideal para irmãos, cada um com o seu próprio progresso\n• Painel para pais: acompanhe o progresso, gira perfis e personalize definições com PIN\n• Escolha operações: decida quais as operações a praticar com recomendações por idade\n• Sincronização na nuvem: sincronize o progresso entre dispositivos com um código simples\n• Multilingue: suporte completo para inglês, norueguês, espanhol e português\n\nConcebida com uma interface divertida e pensada para crianças. Sem anúncios nem compras integradas, apenas aprendizagem divertida.","keywords":"crianças,aprendizagem,matemática,leitura,educação,estudo,adição,subtração,recompensas","marketingUrl":"https://geni.kids","supportUrl":"https://geni.kids","whatsNew":"Esta atualização torna o Geni mais acolhedor, mais claro e mais divertido logo desde o início.\n\nNovidades\n• Onboarding renovado com uma mascote maior, animação ao tocar e cores mais simpáticas\n• Mais avatares disponíveis diretamente no painel principal\n\nMelhorado\n• Um painel mais limpo, com menos distrações e acesso mais claro aos desafios\n• Os cartões de desafios continuam visíveis para que as crianças vejam o que desbloqueiam após a missão de hoje\n\nCorrigido\n• Criar um novo perfil no onboarding leva agora corretamente ao painel principal\n• Foram corrigidos vários problemas no fluxo de onboarding e no ecrã inicial"}
